[
  {
    "kanji": "威厳",
    "kana": "いげん",
    "meaning": "威严",
    "jlpt": "N1",
    "pos": "名詞"
  },
  {
    "kanji": "維持",
    "kana": "いじ",
    "meaning": "维持",
    "jlpt": "N1",
    "pos": "名詞/動詞"
  },
  {
    "kanji": "異性",
    "kana": "いせい",
    "meaning": "异性",
    "jlpt": "N1",
    "pos": "名詞"
  },
  {
    "kanji": "異議",
    "kana": "いぎ",
    "meaning": "异议",
    "jlpt": "N1",
    "pos": "名詞"
  },
  {
    "kanji": "移転",
    "kana": "いてん",
    "meaning": "迁移",
    "jlpt": "N1",
    "pos": "名詞/動詞"
  },
  {
    "kanji": "隠居",
    "kana": "いんきょ",
    "meaning": "隐居",
    "jlpt": "N1",
    "pos": "名詞/動詞"
  },
  {
    "kanji": "運営",
    "kana": "うんえい",
    "meaning": "运营",
    "jlpt": "N1",
    "pos": "名詞/動詞"
  },
  {
    "kanji": "栄誉",
    "kana": "えいよ",
    "meaning": "荣誉",
    "jlpt": "N1",
    "pos": "名詞"
  },
  {
    "kanji": "円滑",
    "kana": "えんかつ",
    "meaning": "圆滑；顺利",
    "jlpt": "N1",
    "pos": "形容動詞"
  },
  {
    "kanji": "架け橋",
    "kana": "かけはし",
    "meaning": "桥梁",
    "jlpt": "N1",
    "pos": "名詞"
  },
  {
    "kanji": "回避",
    "kana": "かいひ",
    "meaning": "回避",
    "jlpt": "N1",
    "pos": "名詞/動詞"
  },
  {
    "kanji": "獲得",
    "kana": "かくとく",
    "meaning": "获得",
    "jlpt": "N1",
    "pos": "名詞/動詞"
  },
  {
    "kanji": "画期的",
    "kana": "かっきてき",
    "meaning": "划时代的",
    "jlpt": "N1",
    "pos": "形容動詞"
  },
  {
    "kanji": "革新",
    "kana": "かくしん",
    "meaning": "革新",
    "jlpt": "N1",
    "pos": "名詞"
  },
  {
    "kanji": "陥る",
    "kana": "おちいる",
    "meaning": "陷入",
    "jlpt": "N1",
    "pos": "動詞・五段"
  },
  {
    "kanji": "寛容",
    "kana": "かんよう",
    "meaning": "宽容",
    "jlpt": "N1",
    "pos": "名詞"
  },
  {
    "kanji": "貫く",
    "kana": "つらぬく",
    "meaning": "贯穿；坚持",
    "jlpt": "N1",
    "pos": "動詞・五段"
  },
  {
    "kanji": "基盤",
    "kana": "きばん",
    "meaning": "基础",
    "jlpt": "N1",
    "pos": "名詞"
  },
  {
    "kanji": "究極",
    "kana": "きゅうきょく",
    "meaning": "终极",
    "jlpt": "N1",
    "pos": "名詞"
  },
  {
    "kanji": "窮屈",
    "kana": "きゅうくつ",
    "meaning": "狭窄；拘束",
    "jlpt": "N1",
    "pos": "形容動詞"
  },
  {
    "kanji": "協調",
    "kana": "きょうちょう",
    "meaning": "协调",
    "jlpt": "N1",
    "pos": "名詞/動詞"
  },
  {
    "kanji": "郷土",
    "kana": "きょうど",
    "meaning": "乡土",
    "jlpt": "N1",
    "pos": "名詞"
  },
  {
    "kanji": "緊迫",
    "kana": "きんぱく",
    "meaning": "紧迫",
    "jlpt": "N1",
    "pos": "名詞"
  },
  {
    "kanji": "駆使",
    "kana": "くし",
    "meaning": "灵活运用",
    "jlpt": "N1",
    "pos": "名詞/動詞"
  },
  {
    "kanji": "契機",
    "kana": "けいき",
    "meaning": "契机",
    "jlpt": "N1",
    "pos": "名詞"
  },
  {
    "kanji": "警報",
    "kana": "けいほう",
    "meaning": "警报",
    "jlpt": "N1",
    "pos": "名詞"
  },
  {
    "kanji": "激減",
    "kana": "げきげん",
    "meaning": "锐减",
    "jlpt": "N1",
    "pos": "名詞/動詞"
  },
  {
    "kanji": "懸念",
    "kana": "けねん",
    "meaning": "担忧",
    "jlpt": "N1",
    "pos": "名詞"
  },
  {
    "kanji": "顧客",
    "kana": "こきゃく",
    "meaning": "顾客",
    "jlpt": "N1",
    "pos": "名詞"
  },
  {
    "kanji": "誤差",
    "kana": "ごさ",
    "meaning": "误差",
    "jlpt": "N1",
    "pos": "名詞"
  },
  {
    "kanji": "控除",
    "kana": "こうじょ",
    "meaning": "扣除",
    "jlpt": "N1",
    "pos": "名詞/動詞"
  },
  {
    "kanji": "講和",
    "kana": "こうわ",
    "meaning": "讲和",
    "jlpt": "N1",
    "pos": "名詞"
  },
  {
    "kanji": "黒字",
    "kana": "くろじ",
    "meaning": "盈余",
    "jlpt": "N1",
    "pos": "名詞"
  },
  {
    "kanji": "混乱",
    "kana": "こんらん",
    "meaning": "混乱",
    "jlpt": "N1",
    "pos": "名詞/動詞"
  },
  {
    "kanji": "削除",
    "kana": "さくじょ",
    "meaning": "删除",
    "jlpt": "N1",
    "pos": "名詞/動詞"
  },
  {
    "kanji": "散在",
    "kana": "さんざい",
    "meaning": "遍布；零散分布",
    "jlpt": "N1",
    "pos": "名詞"
  },
  {
    "kanji": "試行",
    "kana": "しこう",
    "meaning": "试行",
    "jlpt": "N1",
    "pos": "名詞/動詞"
  },
  {
    "kanji": "死刑",
    "kana": "しけい",
    "meaning": "死刑",
    "jlpt": "N1",
    "pos": "名詞"
  },
  {
    "kanji": "私的",
    "kana": "してき",
    "meaning": "私人的",
    "jlpt": "N1",
    "pos": "形容動詞"
  },
  {
    "kanji": "視野",
    "kana": "しや",
    "meaning": "视野",
    "jlpt": "N1",
    "pos": "名詞"
  },
  {
    "kanji": "収拾",
    "kana": "しゅうしゅう",
    "meaning": "收拾（局面）",
    "jlpt": "N1",
    "pos": "名詞/動詞"
  },
  {
    "kanji": "修復",
    "kana": "しゅうふく",
    "meaning": "修复",
    "jlpt": "N1",
    "pos": "名詞/動詞"
  },
  {
    "kanji": "重大",
    "kana": "じゅうだい",
    "meaning": "重大",
    "jlpt": "N1",
    "pos": "形容動詞"
  },
  {
    "kanji": "出動",
    "kana": "しゅつどう",
    "meaning": "出动",
    "jlpt": "N1",
    "pos": "名詞/動詞"
  },
  {
    "kanji": "巡る",
    "kana": "めぐる",
    "meaning": "围绕；循环",
    "jlpt": "N1",
    "pos": "動詞・五段"
  },
  {
    "kanji": "消耗",
    "kana": "しょうもう",
    "meaning": "消耗",
    "jlpt": "N1",
    "pos": "名詞/動詞"
  },
  {
    "kanji": "譲歩",
    "kana": "じょうほ",
    "meaning": "让步",
    "jlpt": "N1",
    "pos": "名詞/動詞"
  },
  {
    "kanji": "侵す",
    "kana": "おかす",
    "meaning": "侵犯",
    "jlpt": "N1",
    "pos": "動詞・五段"
  },
  {
    "kanji": "審査",
    "kana": "しんさ",
    "meaning": "审查",
    "jlpt": "N1",
    "pos": "名詞/動詞"
  },
  {
    "kanji": "陣営",
    "kana": "じんえい",
    "meaning": "阵营",
    "jlpt": "N1",
    "pos": "名詞"
  },
  {
    "kanji": "水準",
    "kana": "すいじゅん",
    "meaning": "水准",
    "jlpt": "N1",
    "pos": "名詞"
  },
  {
    "kanji": "推移",
    "kana": "すいい",
    "meaning": "推移",
    "jlpt": "N1",
    "pos": "名詞"
  },
  {
    "kanji": "是正",
    "kana": "ぜせい",
    "meaning": "纠正",
    "jlpt": "N1",
    "pos": "名詞/動詞"
  },
  {
    "kanji": "措置",
    "kana": "そち",
    "meaning": "措施",
    "jlpt": "N1",
    "pos": "名詞"
  },
  {
    "kanji": "促進",
    "kana": "そくしん",
    "meaning": "促进",
    "jlpt": "N1",
    "pos": "名詞/動詞"
  },
  {
    "kanji": "体系",
    "kana": "たいけい",
    "meaning": "体系",
    "jlpt": "N1",
    "pos": "名詞"
  },
  {
    "kanji": "対処",
    "kana": "たいしょ",
    "meaning": "处理；应对",
    "jlpt": "N1",
    "pos": "名詞/動詞"
  },
  {
    "kanji": "妥協",
    "kana": "だきょう",
    "meaning": "妥协",
    "jlpt": "N1",
    "pos": "名詞/動詞"
  },
  {
    "kanji": "奪う",
    "kana": "うばう",
    "meaning": "抢夺",
    "jlpt": "N1",
    "pos": "動詞・五段"
  },
  {
    "kanji": "蓄える",
    "kana": "たくわえる",
    "meaning": "储存",
    "jlpt": "N1",
    "pos": "動詞・一段"
  },
  {
    "kanji": "蓄積",
    "kana": "ちくせき",
    "meaning": "积累",
    "jlpt": "N1",
    "pos": "名詞/動詞"
  },
  {
    "kanji": "恵まれる",
    "kana": "めぐまれる",
    "meaning": "被赐予；受惠",
    "jlpt": "N1",
    "pos": "動詞・一段"
  },
  {
    "kanji": "停滞",
    "kana": "ていたい",
    "meaning": "停滞",
    "jlpt": "N1",
    "pos": "名詞/動詞"
  },
  {
    "kanji": "徹底",
    "kana": "てってい",
    "meaning": "彻底",
    "jlpt": "N1",
    "pos": "名詞/動詞"
  },
  {
    "kanji": "展開",
    "kana": "てんかい",
    "meaning": "展开",
    "jlpt": "N1",
    "pos": "名詞/動詞"
  },
  {
    "kanji": "投入",
    "kana": "とうにゅう",
    "meaning": "投入",
    "jlpt": "N1",
    "pos": "名詞/動詞"
  },
  {
    "kanji": "到達",
    "kana": "とうたつ",
    "meaning": "到达",
    "jlpt": "N1",
    "pos": "名詞/動詞"
  },
  {
    "kanji": "透明",
    "kana": "とうめい",
    "meaning": "透明",
    "jlpt": "N1",
    "pos": "形容動詞"
  },
  {
    "kanji": "突如",
    "kana": "とつじょ",
    "meaning": "突然",
    "jlpt": "N1",
    "pos": "副詞"
  },
  {
    "kanji": "鈍感",
    "kana": "どんかん",
    "meaning": "迟钝",
    "jlpt": "N1",
    "pos": "形容動詞"
  },
  {
    "kanji": "嘆く",
    "kana": "なげく",
    "meaning": "叹息；悲叹",
    "jlpt": "N1",
    "pos": "動詞・五段"
  },
  {
    "kanji": "軟弱",
    "kana": "なんじゃく",
    "meaning": "软弱",
    "jlpt": "N1",
    "pos": "形容動詞"
  },
  {
    "kanji": "認知",
    "kana": "にんち",
    "meaning": "认知",
    "jlpt": "N1",
    "pos": "名詞"
  },
  {
    "kanji": "粘る",
    "kana": "ねばる",
    "meaning": "坚韧；坚持",
    "jlpt": "N1",
    "pos": "動詞・五段"
  },
  {
    "kanji": "廃棄",
    "kana": "はいき",
    "meaning": "废弃",
    "jlpt": "N1",
    "pos": "名詞/動詞"
  },
  {
    "kanji": "波及",
    "kana": "はきゅう",
    "meaning": "波及",
    "jlpt": "N1",
    "pos": "名詞/動詞"
  },
  {
    "kanji": "発揮",
    "kana": "はっき",
    "meaning": "发挥",
    "jlpt": "N1",
    "pos": "名詞/動詞"
  },
  {
    "kanji": "剥奪",
    "kana": "はくだつ",
    "meaning": "剥夺",
    "jlpt": "N1",
    "pos": "名詞/動詞"
  },
  {
    "kanji": "繁栄",
    "kana": "はんえい",
    "meaning": "繁荣",
    "jlpt": "N1",
    "pos": "名詞"
  },
  {
    "kanji": "繁盛",
    "kana": "はんじょう",
    "meaning": "繁盛",
    "jlpt": "N1",
    "pos": "名詞"
  },
  {
    "kanji": "批判",
    "kana": "ひはん",
    "meaning": "批判",
    "jlpt": "N1",
    "pos": "名詞/動詞"
  },
  {
    "kanji": "頻繁",
    "kana": "ひんぱん",
    "meaning": "频繁",
    "jlpt": "N1",
    "pos": "形容動詞"
  },
  {
    "kanji": "負担",
    "kana": "ふたん",
    "meaning": "负担",
    "jlpt": "N1",
    "pos": "名詞"
  },
  {
    "kanji": "普及",
    "kana": "ふきゅう",
    "meaning": "普及",
    "jlpt": "N1",
    "pos": "名詞/動詞"
  },
  {
    "kanji": "腐敗",
    "kana": "ふはい",
    "meaning": "腐败",
    "jlpt": "N1",
    "pos": "名詞/動詞"
  },
  {
    "kanji": "踏まえる",
    "kana": "ふまえる",
    "meaning": "立足于；基于",
    "jlpt": "N1",
    "pos": "動詞・一段"
  },
  {
    "kanji": "防衛",
    "kana": "ぼうえい",
    "meaning": "防卫",
    "jlpt": "N1",
    "pos": "名詞/動詞"
  },
  {
    "kanji": "補完",
    "kana": "ほかん",
    "meaning": "互补",
    "jlpt": "N1",
    "pos": "名詞/動詞"
  },
  {
    "kanji": "没収",
    "kana": "ぼっしゅう",
    "meaning": "没收",
    "jlpt": "N1",
    "pos": "名詞/動詞"
  },
  {
    "kanji": "誇る",
    "kana": "ほこる",
    "meaning": "夸耀；以...为荣",
    "jlpt": "N1",
    "pos": "動詞・五段"
  },
  {
    "kanji": "紛争",
    "kana": "ふんそう",
    "meaning": "纷争",
    "jlpt": "N1",
    "pos": "名詞"
  },
  {
    "kanji": "円満",
    "kana": "えんまん",
    "meaning": "圆满",
    "jlpt": "N1",
    "pos": "形容動詞"
  },
  {
    "kanji": "疎外",
    "kana": "そがい",
    "meaning": "疏远；排斥",
    "jlpt": "N1",
    "pos": "名詞/動詞"
  },
  {
    "kanji": "陶冶",
    "kana": "とうや",
    "meaning": "陶冶",
    "jlpt": "N1",
    "pos": "名詞/動詞"
  },
  {
    "kanji": "消耗",
    "kana": "しょうもう",
    "meaning": "消耗",
    "jlpt": "N1",
    "pos": "名詞/動詞"
  },
  {
    "kanji": "厳密",
    "kana": "げんみつ",
    "meaning": "严密",
    "jlpt": "N1",
    "pos": "形容動詞"
  },
  {
    "kanji": "裁く",
    "kana": "さばく",
    "meaning": "裁判；评判",
    "jlpt": "N1",
    "pos": "動詞・五段"
  },
  {
    "kanji": "醸す",
    "kana": "かもす",
    "meaning": "酿成；酝酿",
    "jlpt": "N1",
    "pos": "動詞・五段"
  },
  {
    "kanji": "是認",
    "kana": "ぜにん",
    "meaning": "认可",
    "jlpt": "N1",
    "pos": "名詞/動詞"
  },
  {
    "kanji": "諭す",
    "kana": "さとす",
    "meaning": "劝导；开导",
    "jlpt": "N1",
    "pos": "動詞・五段"
  },
  {
    "kanji": "貫徹",
    "kana": "かんてつ",
    "meaning": "贯彻",
    "jlpt": "N1",
    "pos": "名詞/動詞"
  }
]